euring/__about__.py
euring/__init__.py
euring/codes.py
euring/converters.py
euring/data/__init__.py
euring/data/code_table_accuracy_of_coordinates.py
euring/data/code_table_accuracy_of_date.py
euring/data/code_table_accuracy_of_pullus_age.py
euring/data/code_table_age.py
euring/data/code_table_alula.py
euring/data/code_table_bill_method.py
euring/data/code_table_brood_patch.py
euring/data/code_table_brood_size.py
euring/data/code_table_carpal_covert.py
euring/data/code_table_catching_lures.py
euring/data/code_table_catching_method.py
euring/data/code_table_circumstances.py
euring/data/code_table_circumstances_presumed.py
euring/data/code_table_condition.py
euring/data/code_table_euring_code_identifier.py
euring/data/code_table_fat_score_method.py
euring/data/code_table_manipulated.py
euring/data/code_table_metal_ring_information.py
euring/data/code_table_moult.py
euring/data/code_table_moved_before_the_encounter.py
euring/data/code_table_other_marks_information.py
euring/data/code_table_pectoral_muscle_score.py
euring/data/code_table_place_code.py
euring/data/code_table_plumage_code.py
euring/data/code_table_primary_identification_method.py
euring/data/code_table_primary_moult.py
euring/data/code_table_pullus_age.py
euring/data/code_table_ringing_scheme.py
euring/data/code_table_sex.py
euring/data/code_table_sexing_method.py
euring/data/code_table_species.py
euring/data/code_table_state_of_wing_point.py
euring/data/code_table_status.py
euring/data/code_table_tarsus_method.py
euring/data/code_table_verification_of_the_metal_ring.py
euring/data/code_tables.py
euring/data/loader.py
euring/exceptions.py
euring/fields.py
euring/formats.py
euring/main.py
euring/parsing.py
euring/record.py
euring/rules.py
euring/types.py
euring/utils.py
euring-26.4.dist-info/licenses/AUTHORS
euring-26.4.dist-info/licenses/LICENSE
euring-26.4.dist-info/WHEEL
euring-26.4.dist-info/entry_points.txt
euring-26.4.dist-info/METADATA
euring-26.4.dist-info/RECORD
