Metadata-Version: 2.4
Name: euring
Version: 26.4
Summary: A Python library and CLI for decoding, validating, and converting EURING ringing and recovery records.
Keywords: euring,euring2000,euring2000+,euring2020,bird,ringing,ornithology
Author: Dylan Verheul
Author-email: Dylan Verheul <dylan@dyve.net>
License-Expression: BSD-3-Clause
License-File: AUTHORS
License-File: LICENSE
Classifier: Development Status :: 3 - Alpha
Classifier: Intended Audience :: Science/Research
Classifier: Operating System :: OS Independent
Classifier: Programming Language :: Python :: 3
Classifier: Programming Language :: Python :: 3.10
Classifier: Programming Language :: Python :: 3.11
Classifier: Programming Language :: Python :: 3.12
Classifier: Programming Language :: Python :: 3.13
Classifier: Programming Language :: Python :: 3.14
Classifier: Topic :: Scientific/Engineering :: Information Analysis
Classifier: Topic :: Software Development :: Libraries
Classifier: Topic :: Utilities
Requires-Dist: typer>=0.12.0
Requires-Python: >=3.10
Project-URL: Changelog, https://github.com/observation/euring/blob/main/CHANGELOG.md
Project-URL: Documentation, https://euring.readthedocs.io/
Project-URL: Homepage, https://github.com/observation/euring
Project-URL: Issues, https://github.com/observation/euring/issues
Project-URL: Source, https://github.com/observation/euring
